msbinary/__init__.py
msbinary-0.0.4.dist-info/LICENSE.txt
msbinary-0.0.4.dist-info/METADATA
msbinary-0.0.4.dist-info/WHEEL
msbinary-0.0.4.dist-info/top_level.txt
msbinary-0.0.4.dist-info/RECORD
